daylight.cpython-36m-i386-linux-gnu.so
tools/__init__.py
tools/write_version_info.py
daylight-0.1.3.dist-info/WHEEL
daylight-0.1.3.dist-info/METADATA
daylight-0.1.3.dist-info/RECORD
daylight-0.1.3.dist-info/top_level.txt
daylight-0.1.3.dist-info/LICENSE.txt
